pycord/wavelink/__init__.py
pycord/wavelink/abc.py
pycord/wavelink/backoff.py
pycord/wavelink/enums.py
pycord/wavelink/errors.py
pycord/wavelink/player.py
pycord/wavelink/pool.py
pycord/wavelink/queue.py
pycord/wavelink/stats.py
pycord/wavelink/tracks.py
pycord/wavelink/utils.py
pycord/wavelink/websocket.py
pycord/wavelink/ext/spotify/__init__.py
pycord/wavelink/types/__init__.py
pycord/wavelink/types/queue.py
pycord.wavelink-1.0.0b56.dist-info/LICENSE
pycord.wavelink-1.0.0b56.dist-info/METADATA
pycord.wavelink-1.0.0b56.dist-info/WHEEL
pycord.wavelink-1.0.0b56.dist-info/top_level.txt
pycord.wavelink-1.0.0b56.dist-info/RECORD
