Metadata-Version: 2.1
Name: pycord.wavelink
Version: 1.0.0b56
Summary: A robust and powerful Lavalink wrapper for pycord.
Home-page: https://github.com/Pycord-Development/Pycord.Wavelink
Author: Pycord Development
License: MIT
Platform: UNKNOWN
Classifier: License :: OSI Approved :: MIT License
Classifier: Intended Audience :: Developers
Classifier: Natural Language :: English
Classifier: Operating System :: OS Independent
Classifier: Programming Language :: Python :: 3.8
Classifier: Programming Language :: Python :: 3.9
Classifier: Programming Language :: Python :: 3.10
Classifier: Topic :: Internet
Classifier: Topic :: Software Development :: Libraries
Classifier: Topic :: Software Development :: Libraries :: Python Modules
Classifier: Topic :: Utilities
License-File: LICENSE
Requires-Dist: py-cord (>=2.0.0a)
Requires-Dist: aiohttp (<4.0.0,>=3.6.0)
Provides-Extra: docs
Requires-Dist: sphinx (==4.3.2) ; extra == 'docs'
Requires-Dist: sphinxcontrib-trio (==1.1.2) ; extra == 'docs'
Requires-Dist: sphinxcontrib-websupport ; extra == 'docs'
Provides-Extra: speed
Requires-Dist: orjson (>=3.5.4) ; extra == 'speed'
Requires-Dist: aiodns (>=1.1) ; extra == 'speed'
Requires-Dist: Brotlipy ; extra == 'speed'
Requires-Dist: cchardet ; extra == 'speed'
Provides-Extra: voice
Requires-Dist: PyNaCl (<1.6,>=1.3.0) ; extra == 'voice'
